{
    "@context": {
        "as": "http://www.w3.org/ns/activitystreams#",
        "blog": "http://vocab.amy.so/blog#"
    },
    "replicated": "Post",
    "as:name": "Rice noodles, edamame, broccoli, kale, mushrooms, miso; homemade ginger beer",
    "as:tag": [
        "noodles",
        "vegetables"
    ],
    "@type": [
        "blog:Consumption"
    ],
    "as:published": "2016-08-01T21:03:22-04:00",
    "@id": "http://blog.rhiaro.co.uk/rice-noodles-edamame",
    "http://xmlns.com/foaf/0.1/isPrimaryTopicOf": {
        "@id": "http://rhiaro.co.uk/2016/08/rice-noodles"
    },
    "http://purl.org/dc/terms/created": {
        "@value": "2016-08-01T21:03:22-04:00",
        "@type": "xsd:dateTime"
    }
}