{
    "@context": {
        "as": "http://www.w3.org/ns/activitystreams#",
        "blog": "http://vocab.amy.so/blog#"
    },
    "replicated": "Post",
    "as:name": "Half a coconut (Dosa Factory)",
    "as:tag": [
        "dosa factory",
        "coconut",
        "fruit",
        "csarven"
    ],
    "@type": [
        "blog:Consumption"
    ],
    "as:published": "2016-09-03T14:27:59-04:00",
    "@id": "http://blog.rhiaro.co.uk/half-coconut-dosa",
    "http://xmlns.com/foaf/0.1/isPrimaryTopicOf": {
        "@id": "http://rhiaro.co.uk/2016/09/half-coconut-dosa"
    },
    "http://purl.org/dc/terms/created": {
        "@value": "2016-09-03T14:27:59-04:00",
        "@type": "xsd:dateTime"
    }
}