{
    "@context": {
        "as": "http://www.w3.org/ns/activitystreams#",
        "blog": "http://vocab.amy.so/blog#"
    },
    "as:summary": "Regret (Veggie Galaxy)",
    "blog:cost": "$20",
    "as:tag": [
        "food",
        "restaurant",
        "vegan",
        "veggie galaxy"
    ],
    "@type": [
        "blog:Acquisition"
    ],
    "as:published": "2016-01-06T17:46:21-05:00",
    "@id": "http://blog.rhiaro.co.uk/568dc3b2cfec6",
    "http://xmlns.com/foaf/0.1/isPrimaryTopicOf": {
        "@id": "http://rhiaro.co.uk/2016/01/568dc3b2cfec6"
    },
    "http://purl.org/dc/terms/created": {
        "@value": "2016-01-06T17:46:21-05:00",
        "@type": "xsd:dateTime"
    }
}