{
    "@context": {
        "as": "http://www.w3.org/ns/activitystreams#",
        "blog": "http://vocab.amy.so/blog#"
    },
    "replicated": "Post",
    "as:name": "Granola and almond milk. Coffee.",
    "as:tag": [
        "coffee"
    ],
    "@type": [
        "blog:Consumption"
    ],
    "as:published": "2016-01-15T11:10:31-05:00",
    "@id": "http://blog.rhiaro.co.uk/granola-almond",
    "http://xmlns.com/foaf/0.1/isPrimaryTopicOf": {
        "@id": "http://rhiaro.co.uk/2016/01/granola-almond"
    },
    "http://purl.org/dc/terms/created": {
        "@value": "2016-01-15T11:10:31-05:00",
        "@type": "xsd:dateTime"
    }
}