{
    "h": "entry",
    "bookmark-of": "https://petermolnar.eu/debian-lightweight-mailserver-postfix-dovecot-dspam/",
    "category": [
        "email",
        "ownyourdata"
    ],
    "@context": "http://rhiaro.co.uk/vocab",
    "published": "2016-03-01T20:14:30+00:00",
    "@id": "http://blog.rhiaro.co.uk/56d5f826199d2",
    "http://xmlns.com/foaf/0.1/isPrimaryTopicOf": {
        "@id": "http://rhiaro.co.uk/2016/03/56d5f826199d2"
    },
    "http://purl.org/dc/terms/created": {
        "@value": "2016-03-01T20:14:30+00:00",
        "@type": "xsd:dateTime"
    }
}