{
    "@context": {
        "as": "http://www.w3.org/ns/activitystreams#",
        "blog": "http://vocab.amy.so/blog#"
    },
    "replicated": "Post",
    "as:name": "Brown rice, salad, bok choi, carrots, tofu, chillis, coconut water (Medium)",
    "as:tag": [
        "rice",
        "medium",
        "sf",
        "vegetables"
    ],
    "@type": [
        "blog:Consumption"
    ],
    "as:published": "2016-06-10T12:12:52-07:00",
    "@id": "http://blog.rhiaro.co.uk/brown-rice-salad",
    "http://xmlns.com/foaf/0.1/isPrimaryTopicOf": {
        "@id": "http://rhiaro.co.uk/2016/06/brown-rice-salad"
    },
    "http://purl.org/dc/terms/created": {
        "@value": "2016-06-10T12:12:52-07:00",
        "@type": "xsd:dateTime"
    }
}